<?xml version="1.0" encoding="UTF-8"?>
<wgt:form xmlns:wgt="http://n2oapp.net/framework/config/schema/n2o-widget-2.0"
          xmlns:fs="http://n2oapp.net/framework/config/schema/fieldset-2.0"
          xmlns:ctrl="http://n2oapp.net/framework/config/schema/n2o-control-1.0">

    <wgt:name>Порционник на питание больных</wgt:name>
    <wgt:object-id>hosp_report</wgt:object-id>
    <wgt:edit model="default" form-submit-label="Сформировать отчёт" after-submit="closeModal">
        <wgt:a href="${rmis.report.url}?__report=1-84.rptdesign&amp;to_dt=:toDt:&amp;time=:time:&amp;clinic_id=:org.id:&amp;department_id=:department.id:&amp;__format=pdf"
               target="newWindow"/>
    </wgt:edit>
    <fs:field-set>

        <ctrl:hidden id="org.id" default-value="#{org.id}"/>

        <ctrl:date-time id="toDt" label="Дата" required="true" format="DD.MM.YYYY"/>

        <ctrl:masked-input id="time" mask="99:99" label="Время" required="true">
            <ctrl:validations>
                <ctrl:validation ref-id="validateTime" side="client"/>
            </ctrl:validations>
        </ctrl:masked-input>

        <ctrl:classifier id="department" label="Отделение" required="true">
            <ctrl:query query-id="hosp_department" value-field-id="id" label-field-id="name">
                <ctrl:pre-filters>
                    <ctrl:pre-filter field-id="organizationId" ref="org.id"/>
                </ctrl:pre-filters>
            </ctrl:query>
            <ctrl:default-model>
                <ctrl:value field-id="id">#{dep.id?}</ctrl:value>
                <ctrl:value field-id="name">#{dep.name?}</ctrl:value>
            </ctrl:default-model>
        </ctrl:classifier>

    </fs:field-set>
</wgt:form>

