<?xml version="1.0" encoding="UTF-8"?>
<wgt:form xmlns:wgt="http://n2oapp.net/framework/config/schema/n2o-widget-2.0" xmlns:fs="http://n2oapp.net/framework/config/schema/fieldset-2.0">
    <wgt:name>направление на гематологический, общеклинический анализ    ф201у</wgt:name>
    <wgt:object-id>report</wgt:object-id>
    <wgt:edit model="default" form-submit-label="Сформировать отчёт" after-submit="closeModal">
        <wgt:a href="${rmis.report.url}?__report=201y_napr.rptdesign&amp;referral_id=:referral_id:&amp;form_type_id=:form_type_id:&amp;is_qrcode=:is_qrcode:&amp;__format=pdf" />
    </wgt:edit>
    <fs:field-set xmlns:ctrl="http://n2oapp.net/framework/config/schema/n2o-control-1.0">
        <ctrl:input-text id="referral_id" label="referral_id" visible="true" required="true" />
        <ctrl:input-text id="form_type_id" label="form_type_id" visible="true" />
        <ctrl:input-text id="is_qrcode" label="is_qrcode" visible="true" required="false" />
    </fs:field-set>
</wgt:form>

