<?xml version='1.0' encoding='UTF-8'?>
<query xmlns="http://n2oapp.net/framework/config/schema/query-2.0"
       xmlns:n2o="http://n2oapp.net/framework/config/schema/n2o-query-executions-1.0">
    <object-id>table</object-id>
    <execution>
        <n2o:java-criteria bean-name="tableService"
                           criteria-class="net.n2oapp.framework.config.admin.metadata.manager.object.criteria.TableCriteria"/>
    </execution>
    <fields>
        <field>
            <id>id</id>
            <domain>String</domain>
            <sorting unavailable="true"/>
        </field>
        <field>
            <id>pageId</id>
            <domain>String</domain>
            <sorting unavailable="true"/>
        </field>
        <field>
            <id>widgetId</id>
            <domain>String</domain>
            <sorting unavailable="true"/>
        </field>
        <field>
            <id>name</id>
            <name>Наименование</name>
            <domain>String</domain>
            <search unavailable="true"/>
            <sorting unavailable="true"/>
        </field>
        <field>
            <id>name_compiled</id>
            <name>Наименование</name>
            <domain>String</domain>
        </field>
        <field>
            <id>field</id>
            <name>Идентификатор</name>
            <domain>String</domain>
            <search unavailable="true"/>
            <sorting unavailable="true"/>
        </field>
        <field>
            <id>column</id>
            <name>Столбец</name>
            <domain>Boolean</domain>
        </field>
        <field>
            <id>query.id</id>
            <domain>string</domain>
        </field>
        <field>
            <id>filter</id>
            <name>Фильтр</name>
            <domain>Boolean</domain>
            <search unavailable="true"/>
            <sorting unavailable="true"/>
        </field>
    </fields>
</query>